LICENSE
MANIFEST.in
README.rst
setup.py
django_ohm2_accounts_light.egg-info/PKG-INFO
django_ohm2_accounts_light.egg-info/SOURCES.txt
django_ohm2_accounts_light.egg-info/dependency_links.txt
django_ohm2_accounts_light.egg-info/requires.txt
django_ohm2_accounts_light.egg-info/top_level.txt
docs/INFO.txt
ohm2_accounts_light/__init__.py
ohm2_accounts_light/admin.py
ohm2_accounts_light/apps.py
ohm2_accounts_light/decorators.py
ohm2_accounts_light/dispatcher.py
ohm2_accounts_light/errors.py
ohm2_accounts_light/managers.py
ohm2_accounts_light/models.py
ohm2_accounts_light/serializers.py
ohm2_accounts_light/settings.py
ohm2_accounts_light/tests.py
ohm2_accounts_light/urls.py
ohm2_accounts_light/utils.py
ohm2_accounts_light/views.py
ohm2_accounts_light/api/v1/dispatcher.py
ohm2_accounts_light/api/v1/errors.py
ohm2_accounts_light/api/v1/settings.py
ohm2_accounts_light/api/v1/urls.py
ohm2_accounts_light/api/v1/views.py
ohm2_accounts_light/api/v1/__pycache__/dispatcher.cpython-35.pyc
ohm2_accounts_light/api/v1/__pycache__/errors.cpython-35.pyc
ohm2_accounts_light/api/v1/__pycache__/settings.cpython-35.pyc
ohm2_accounts_light/api/v1/__pycache__/urls.cpython-35.pyc
ohm2_accounts_light/api/v1/__pycache__/views.cpython-35.pyc
ohm2_accounts_light/migrations/0001_initial.py
ohm2_accounts_light/migrations/0001_squashed_0003_auto_20181119_2119.py
ohm2_accounts_light/migrations/0002_auto_20181119_2052.py
ohm2_accounts_light/migrations/0003_auto_20181119_2119.py
ohm2_accounts_light/migrations/__init__.py
ohm2_accounts_light/migrations/__pycache__/0001_initial.cpython-35.pyc
ohm2_accounts_light/migrations/__pycache__/0001_squashed_0003_auto_20181119_2119.cpython-35.pyc
ohm2_accounts_light/migrations/__pycache__/0002_auto_20181119_2052.cpython-35.pyc
ohm2_accounts_light/migrations/__pycache__/0003_auto_20181119_2119.cpython-35.pyc
ohm2_accounts_light/migrations/__pycache__/__init__.cpython-35.pyc
ohm2_accounts_light/pipelines/.DS_Store
ohm2_accounts_light/pipelines/login/default.py
ohm2_accounts_light/pipelines/login/__pycache__/default.cpython-35.pyc
ohm2_accounts_light/pipelines/logout/default.py
ohm2_accounts_light/pipelines/logout/__pycache__/default.cpython-35.pyc
ohm2_accounts_light/pipelines/signup/.DS_Store
